{
  "openapi": "3.0.1",
  "info": {
    "title": "backend",
    "version": "1.0"
  },
  "paths": {
    "/api/admin/evaluations/events": {
      "post": {
        "tags": [
          "AdminEvaluation"
        ],
        "requestBody": {
          "content": {
            "application/json": {
              "schema": {
                "$ref": "#/components/schemas/CreateEventDto"
              }
            },
            "text/json": {
              "schema": {
                "$ref": "#/components/schemas/CreateEventDto"
              }
            },
            "application/*+json": {
              "schema": {
                "$ref": "#/components/schemas/CreateEventDto"
              }
            }
          }
        },
        "responses": {
          "200": {
            "description": "OK",
            "content": {
              "text/plain": {
                "schema": {
                  "$ref": "#/components/schemas/EvaluationEventDto"
                }
              },
              "application/json": {
                "schema": {
                  "$ref": "#/components/schemas/EvaluationEventDto"
                }
              },
              "text/json": {
                "schema": {
                  "$ref": "#/components/schemas/EvaluationEventDto"
                }
              }
            }
          }
        }
      },
      "get": {
        "tags": [
          "AdminEvaluation"
        ],
        "responses": {
          "200": {
            "description": "OK",
            "content": {
              "text/plain": {
                "schema": {
                  "type": "array",
                  "items": {
                    "$ref": "#/components/schemas/EvaluationEventDto"
                  }
                }
              },
              "application/json": {
                "schema": {
                  "type": "array",
                  "items": {
                    "$ref": "#/components/schemas/EvaluationEventDto"
                  }
                }
              },
              "text/json": {
                "schema": {
                  "type": "array",
                  "items": {
                    "$ref": "#/components/schemas/EvaluationEventDto"
                  }
                }
              }
            }
          }
        }
      }
    },
    "/api/admin/evaluations/events/{id}": {
      "get": {
        "tags": [
          "AdminEvaluation"
        ],
        "parameters": [
          {
            "name": "id",
            "in": "path",
            "required": true,
            "schema": {
              "type": "integer",
              "format": "int32"
            }
          }
        ],
        "responses": {
          "200": {
            "description": "OK",
            "content": {
              "text/plain": {
                "schema": {
                  "$ref": "#/components/schemas/EvaluationEventDto"
                }
              },
              "application/json": {
                "schema": {
                  "$ref": "#/components/schemas/EvaluationEventDto"
                }
              },
              "text/json": {
                "schema": {
                  "$ref": "#/components/schemas/EvaluationEventDto"
                }
              }
            }
          }
        }
      },
      "put": {
        "tags": [
          "AdminEvaluation"
        ],
        "parameters": [
          {
            "name": "id",
            "in": "path",
            "required": true,
            "schema": {
              "type": "integer",
              "format": "int32"
            }
          }
        ],
        "requestBody": {
          "content": {
            "application/json": {
              "schema": {
                "$ref": "#/components/schemas/UpdateEventDto"
              }
            },
            "text/json": {
              "schema": {
                "$ref": "#/components/schemas/UpdateEventDto"
              }
            },
            "application/*+json": {
              "schema": {
                "$ref": "#/components/schemas/UpdateEventDto"
              }
            }
          }
        },
        "responses": {
          "200": {
            "description": "OK",
            "content": {
              "text/plain": {
                "schema": {
                  "$ref": "#/components/schemas/EvaluationEventDto"
                }
              },
              "application/json": {
                "schema": {
                  "$ref": "#/components/schemas/EvaluationEventDto"
                }
              },
              "text/json": {
                "schema": {
                  "$ref": "#/components/schemas/EvaluationEventDto"
                }
              }
            }
          }
        }
      },
      "delete": {
        "tags": [
          "AdminEvaluation"
        ],
        "parameters": [
          {
            "name": "id",
            "in": "path",
            "required": true,
            "schema": {
              "type": "integer",
              "format": "int32"
            }
          }
        ],
        "responses": {
          "200": {
            "description": "OK"
          }
        }
      }
    },
    "/api/admin/evaluations/assign-panel": {
      "post": {
        "tags": [
          "AdminEvaluation"
        ],
        "requestBody": {
          "content": {
            "application/json": {
              "schema": {
                "$ref": "#/components/schemas/AssignPanelDto"
              }
            },
            "text/json": {
              "schema": {
                "$ref": "#/components/schemas/AssignPanelDto"
              }
            },
            "application/*+json": {
              "schema": {
                "$ref": "#/components/schemas/AssignPanelDto"
              }
            }
          }
        },
        "responses": {
          "200": {
            "description": "OK",
            "content": {
              "text/plain": {
                "schema": {
                  "$ref": "#/components/schemas/GroupEvaluationDto"
                }
              },
              "application/json": {
                "schema": {
                  "$ref": "#/components/schemas/GroupEvaluationDto"
                }
              },
              "text/json": {
                "schema": {
                  "$ref": "#/components/schemas/GroupEvaluationDto"
                }
              }
            }
          }
        }
      }
    },
    "/api/admin/evaluations/group-evaluations/{id}": {
      "get": {
        "tags": [
          "AdminEvaluation"
        ],
        "parameters": [
          {
            "name": "id",
            "in": "path",
            "required": true,
            "schema": {
              "type": "integer",
              "format": "int32"
            }
          }
        ],
        "responses": {
          "200": {
            "description": "OK",
            "content": {
              "text/plain": {
                "schema": {
                  "$ref": "#/components/schemas/GroupEvaluationDto"
                }
              },
              "application/json": {
                "schema": {
                  "$ref": "#/components/schemas/GroupEvaluationDto"
                }
              },
              "text/json": {
                "schema": {
                  "$ref": "#/components/schemas/GroupEvaluationDto"
                }
              }
            }
          }
        }
      }
    },
    "/api/admin/evaluations/events/{eventId}/evaluations": {
      "get": {
        "tags": [
          "AdminEvaluation"
        ],
        "parameters": [
          {
            "name": "eventId",
            "in": "path",
            "required": true,
            "schema": {
              "type": "integer",
              "format": "int32"
            }
          }
        ],
        "responses": {
          "200": {
            "description": "OK",
            "content": {
              "text/plain": {
                "schema": {
                  "type": "array",
                  "items": {
                    "$ref": "#/components/schemas/GroupEvaluationDto"
                  }
                }
              },
              "application/json": {
                "schema": {
                  "type": "array",
                  "items": {
                    "$ref": "#/components/schemas/GroupEvaluationDto"
                  }
                }
              },
              "text/json": {
                "schema": {
                  "type": "array",
                  "items": {
                    "$ref": "#/components/schemas/GroupEvaluationDto"
                  }
                }
              }
            }
          }
        }
      }
    },
    "/api/admin/evaluations/panels/{panelId}/evaluations": {
      "get": {
        "tags": [
          "AdminEvaluation"
        ],
        "parameters": [
          {
            "name": "panelId",
            "in": "path",
            "required": true,
            "schema": {
              "type": "integer",
              "format": "int32"
            }
          }
        ],
        "responses": {
          "200": {
            "description": "OK",
            "content": {
              "text/plain": {
                "schema": {
                  "type": "array",
                  "items": {
                    "$ref": "#/components/schemas/GroupEvaluationDto"
                  }
                }
              },
              "application/json": {
                "schema": {
                  "type": "array",
                  "items": {
                    "$ref": "#/components/schemas/GroupEvaluationDto"
                  }
                }
              },
              "text/json": {
                "schema": {
                  "type": "array",
                  "items": {
                    "$ref": "#/components/schemas/GroupEvaluationDto"
                  }
                }
              }
            }
          }
        }
      }
    },
    "/api/admin/evaluations/dashboard": {
      "get": {
        "tags": [
          "AdminEvaluation"
        ],
        "responses": {
          "200": {
            "description": "OK",
            "content": {
              "text/plain": {
                "schema": {
                  "$ref": "#/components/schemas/AdminDashboardDto"
                }
              },
              "application/json": {
                "schema": {
                  "$ref": "#/components/schemas/AdminDashboardDto"
                }
              },
              "text/json": {
                "schema": {
                  "$ref": "#/components/schemas/AdminDashboardDto"
                }
              }
            }
          }
        }
      }
    },
    "/api/admin/panels": {
      "post": {
        "tags": [
          "AdminPanel"
        ],
        "requestBody": {
          "content": {
            "application/json": {
              "schema": {
                "$ref": "#/components/schemas/CreatePanelDto"
              }
            },
            "text/json": {
              "schema": {
                "$ref": "#/components/schemas/CreatePanelDto"
              }
            },
            "application/*+json": {
              "schema": {
                "$ref": "#/components/schemas/CreatePanelDto"
              }
            }
          }
        },
        "responses": {
          "200": {
            "description": "OK",
            "content": {
              "text/plain": {
                "schema": {
                  "$ref": "#/components/schemas/PanelDto"
                }
              },
              "application/json": {
                "schema": {
                  "$ref": "#/components/schemas/PanelDto"
                }
              },
              "text/json": {
                "schema": {
                  "$ref": "#/components/schemas/PanelDto"
                }
              }
            }
          }
        }
      },
      "get": {
        "tags": [
          "AdminPanel"
        ],
        "responses": {
          "200": {
            "description": "OK",
            "content": {
              "text/plain": {
                "schema": {
                  "type": "array",
                  "items": {
                    "$ref": "#/components/schemas/PanelDto"
                  }
                }
              },
              "application/json": {
                "schema": {
                  "type": "array",
                  "items": {
                    "$ref": "#/components/schemas/PanelDto"
                  }
                }
              },
              "text/json": {
                "schema": {
                  "type": "array",
                  "items": {
                    "$ref": "#/components/schemas/PanelDto"
                  }
                }
              }
            }
          }
        }
      }
    },
    "/api/admin/panels/{id}": {
      "get": {
        "tags": [
          "AdminPanel"
        ],
        "parameters": [
          {
            "name": "id",
            "in": "path",
            "required": true,
            "schema": {
              "type": "integer",
              "format": "int32"
            }
          }
        ],
        "responses": {
          "200": {
            "description": "OK",
            "content": {
              "text/plain": {
                "schema": {
                  "$ref": "#/components/schemas/PanelDto"
                }
              },
              "application/json": {
                "schema": {
                  "$ref": "#/components/schemas/PanelDto"
                }
              },
              "text/json": {
                "schema": {
                  "$ref": "#/components/schemas/PanelDto"
                }
              }
            }
          }
        }
      },
      "put": {
        "tags": [
          "AdminPanel"
        ],
        "parameters": [
          {
            "name": "id",
            "in": "path",
            "required": true,
            "schema": {
              "type": "integer",
              "format": "int32"
            }
          }
        ],
        "requestBody": {
          "content": {
            "application/json": {
              "schema": {
                "$ref": "#/components/schemas/UpdatePanelDto"
              }
            },
            "text/json": {
              "schema": {
                "$ref": "#/components/schemas/UpdatePanelDto"
              }
            },
            "application/*+json": {
              "schema": {
                "$ref": "#/components/schemas/UpdatePanelDto"
              }
            }
          }
        },
        "responses": {
          "200": {
            "description": "OK",
            "content": {
              "text/plain": {
                "schema": {
                  "$ref": "#/components/schemas/PanelDto"
                }
              },
              "application/json": {
                "schema": {
                  "$ref": "#/components/schemas/PanelDto"
                }
              },
              "text/json": {
                "schema": {
                  "$ref": "#/components/schemas/PanelDto"
                }
              }
            }
          }
        }
      },
      "delete": {
        "tags": [
          "AdminPanel"
        ],
        "parameters": [
          {
            "name": "id",
            "in": "path",
            "required": true,
            "schema": {
              "type": "integer",
              "format": "int32"
            }
          }
        ],
        "responses": {
          "200": {
            "description": "OK"
          }
        }
      }
    },
    "/api/admin/panels/byEvent/{eventId}": {
      "get": {
        "tags": [
          "AdminPanel"
        ],
        "parameters": [
          {
            "name": "eventId",
            "in": "path",
            "required": true,
            "schema": {
              "type": "integer",
              "format": "int32"
            }
          }
        ],
        "responses": {
          "200": {
            "description": "OK",
            "content": {
              "text/plain": {
                "schema": {
                  "type": "array",
                  "items": {
                    "$ref": "#/components/schemas/PanelDto"
                  }
                }
              },
              "application/json": {
                "schema": {
                  "type": "array",
                  "items": {
                    "$ref": "#/components/schemas/PanelDto"
                  }
                }
              },
              "text/json": {
                "schema": {
                  "type": "array",
                  "items": {
                    "$ref": "#/components/schemas/PanelDto"
                  }
                }
              }
            }
          }
        }
      }
    },
    "/api/admin/rubrics": {
      "post": {
        "tags": [
          "AdminRubric"
        ],
        "requestBody": {
          "content": {
            "application/json": {
              "schema": {
                "$ref": "#/components/schemas/CreateRubricDto"
              }
            },
            "text/json": {
              "schema": {
                "$ref": "#/components/schemas/CreateRubricDto"
              }
            },
            "application/*+json": {
              "schema": {
                "$ref": "#/components/schemas/CreateRubricDto"
              }
            }
          }
        },
        "responses": {
          "200": {
            "description": "OK",
            "content": {
              "text/plain": {
                "schema": {
                  "$ref": "#/components/schemas/EvaluationRubricDto"
                }
              },
              "application/json": {
                "schema": {
                  "$ref": "#/components/schemas/EvaluationRubricDto"
                }
              },
              "text/json": {
                "schema": {
                  "$ref": "#/components/schemas/EvaluationRubricDto"
                }
              }
            }
          }
        }
      },
      "get": {
        "tags": [
          "AdminRubric"
        ],
        "responses": {
          "200": {
            "description": "OK"
          }
        }
      }
    },
    "/api/admin/rubrics/{id}": {
      "get": {
        "tags": [
          "AdminRubric"
        ],
        "parameters": [
          {
            "name": "id",
            "in": "path",
            "required": true,
            "schema": {
              "type": "integer",
              "format": "int32"
            }
          }
        ],
        "responses": {
          "200": {
            "description": "OK",
            "content": {
              "text/plain": {
                "schema": {
                  "$ref": "#/components/schemas/EvaluationRubricDto"
                }
              },
              "application/json": {
                "schema": {
                  "$ref": "#/components/schemas/EvaluationRubricDto"
                }
              },
              "text/json": {
                "schema": {
                  "$ref": "#/components/schemas/EvaluationRubricDto"
                }
              }
            }
          }
        }
      },
      "put": {
        "tags": [
          "AdminRubric"
        ],
        "parameters": [
          {
            "name": "id",
            "in": "path",
            "required": true,
            "schema": {
              "type": "integer",
              "format": "int32"
            }
          }
        ],
        "requestBody": {
          "content": {
            "application/json": {
              "schema": {
                "$ref": "#/components/schemas/UpdateRubricDto"
              }
            },
            "text/json": {
              "schema": {
                "$ref": "#/components/schemas/UpdateRubricDto"
              }
            },
            "application/*+json": {
              "schema": {
                "$ref": "#/components/schemas/UpdateRubricDto"
              }
            }
          }
        },
        "responses": {
          "200": {
            "description": "OK",
            "content": {
              "text/plain": {
                "schema": {
                  "$ref": "#/components/schemas/EvaluationRubricDto"
                }
              },
              "application/json": {
                "schema": {
                  "$ref": "#/components/schemas/EvaluationRubricDto"
                }
              },
              "text/json": {
                "schema": {
                  "$ref": "#/components/schemas/EvaluationRubricDto"
                }
              }
            }
          }
        }
      },
      "delete": {
        "tags": [
          "AdminRubric"
        ],
        "parameters": [
          {
            "name": "id",
            "in": "path",
            "required": true,
            "schema": {
              "type": "integer",
              "format": "int32"
            }
          }
        ],
        "responses": {
          "200": {
            "description": "OK"
          }
        }
      }
    },
    "/api/admin/rubrics/normalized-grades": {
      "get": {
        "tags": [
          "AdminRubric"
        ],
        "responses": {
          "200": {
            "description": "OK",
            "content": {
              "text/plain": {
                "schema": {
                  "type": "array",
                  "items": {
                    "$ref": "#/components/schemas/NormalizedGradeDto"
                  }
                }
              },
              "application/json": {
                "schema": {
                  "type": "array",
                  "items": {
                    "$ref": "#/components/schemas/NormalizedGradeDto"
                  }
                }
              },
              "text/json": {
                "schema": {
                  "type": "array",
                  "items": {
                    "$ref": "#/components/schemas/NormalizedGradeDto"
                  }
                }
              }
            }
          }
        }
      }
    },
    "/api/auth/login": {
      "post": {
        "tags": [
          "Auth"
        ],
        "requestBody": {
          "content": {
            "application/json": {
              "schema": {
                "$ref": "#/components/schemas/LoginDto"
              }
            },
            "text/json": {
              "schema": {
                "$ref": "#/components/schemas/LoginDto"
              }
            },
            "application/*+json": {
              "schema": {
                "$ref": "#/components/schemas/LoginDto"
              }
            }
          }
        },
        "responses": {
          "200": {
            "description": "OK"
          }
        }
      }
    },
    "/api/auth/register/admin": {
      "post": {
        "tags": [
          "Auth"
        ],
        "requestBody": {
          "content": {
            "application/json": {
              "schema": {
                "$ref": "#/components/schemas/RegisterAdminDto"
              }
            },
            "text/json": {
              "schema": {
                "$ref": "#/components/schemas/RegisterAdminDto"
              }
            },
            "application/*+json": {
              "schema": {
                "$ref": "#/components/schemas/RegisterAdminDto"
              }
            }
          }
        },
        "responses": {
          "200": {
            "description": "OK"
          }
        }
      }
    },
    "/api/auth/register/teacher": {
      "post": {
        "tags": [
          "Auth"
        ],
        "requestBody": {
          "content": {
            "application/json": {
              "schema": {
                "$ref": "#/components/schemas/RegisterTeacherDto"
              }
            },
            "text/json": {
              "schema": {
                "$ref": "#/components/schemas/RegisterTeacherDto"
              }
            },
            "application/*+json": {
              "schema": {
                "$ref": "#/components/schemas/RegisterTeacherDto"
              }
            }
          }
        },
        "responses": {
          "200": {
            "description": "OK"
          }
        }
      }
    },
    "/api/auth/register/student": {
      "post": {
        "tags": [
          "Auth"
        ],
        "requestBody": {
          "content": {
            "application/json": {
              "schema": {
                "$ref": "#/components/schemas/RegisterStudentDto"
              }
            },
            "text/json": {
              "schema": {
                "$ref": "#/components/schemas/RegisterStudentDto"
              }
            },
            "application/*+json": {
              "schema": {
                "$ref": "#/components/schemas/RegisterStudentDto"
              }
            }
          }
        },
        "responses": {
          "200": {
            "description": "OK"
          }
        }
      }
    },
    "/api/auth/teachers": {
      "get": {
        "tags": [
          "Auth"
        ],
        "responses": {
          "200": {
            "description": "OK"
          }
        }
      }
    },
    "/api/chat/group/{groupId}": {
      "get": {
        "tags": [
          "Chat"
        ],
        "parameters": [
          {
            "name": "groupId",
            "in": "path",
            "required": true,
            "schema": {
              "type": "integer",
              "format": "int32"
            }
          },
          {
            "name": "limit",
            "in": "query",
            "schema": {
              "type": "integer",
              "format": "int32"
            }
          },
          {
            "name": "before",
            "in": "query",
            "schema": {
              "type": "string",
              "format": "date-time"
            }
          }
        ],
        "responses": {
          "200": {
            "description": "OK"
          }
        }
      }
    },
    "/api/chat/mark-read/{groupId}": {
      "post": {
        "tags": [
          "Chat"
        ],
        "parameters": [
          {
            "name": "groupId",
            "in": "path",
            "required": true,
            "schema": {
              "type": "integer",
              "format": "int32"
            }
          }
        ],
        "responses": {
          "200": {
            "description": "OK"
          }
        }
      }
    },
    "/api/chat/unread-count": {
      "get": {
        "tags": [
          "Chat"
        ],
        "responses": {
          "200": {
            "description": "OK"
          }
        }
      }
    },
    "/api/chat/unread-by-group": {
      "get": {
        "tags": [
          "Chat"
        ],
        "responses": {
          "200": {
            "description": "OK"
          }
        }
      }
    },
    "/api/groups/student/{studentId}": {
      "get": {
        "tags": [
          "Group"
        ],
        "parameters": [
          {
            "name": "studentId",
            "in": "path",
            "required": true,
            "schema": {
              "type": "integer",
              "format": "int32"
            }
          }
        ],
        "responses": {
          "200": {
            "description": "OK"
          }
        }
      }
    },
    "/api/groups/{groupId}": {
      "get": {
        "tags": [
          "Group"
        ],
        "parameters": [
          {
            "name": "groupId",
            "in": "path",
            "required": true,
            "schema": {
              "type": "integer",
              "format": "int32"
            }
          }
        ],
        "responses": {
          "200": {
            "description": "OK"
          }
        }
      }
    },
    "/api/groups": {
      "post": {
        "tags": [
          "Group"
        ],
        "requestBody": {
          "content": {
            "application/json": {
              "schema": {
                "$ref": "#/components/schemas/CreateGroupDto"
              }
            },
            "text/json": {
              "schema": {
                "$ref": "#/components/schemas/CreateGroupDto"
              }
            },
            "application/*+json": {
              "schema": {
                "$ref": "#/components/schemas/CreateGroupDto"
              }
            }
          }
        },
        "responses": {
          "200": {
            "description": "OK"
          }
        }
      }
    },
    "/api/groups/student/search": {
      "get": {
        "tags": [
          "Group"
        ],
        "parameters": [
          {
            "name": "email",
            "in": "query",
            "schema": {
              "type": "string"
            }
          }
        ],
        "responses": {
          "200": {
            "description": "OK"
          }
        }
      }
    },
    "/api/groups/supervision-status": {
      "get": {
        "tags": [
          "Group"
        ],
        "parameters": [
          {
            "name": "ids",
            "in": "query",
            "schema": {
              "type": "string"
            }
          }
        ],
        "responses": {
          "200": {
            "description": "OK"
          }
        }
      }
    },
    "/api/groups/cleanup/{acceptedGroupId}": {
      "post": {
        "tags": [
          "Group"
        ],
        "parameters": [
          {
            "name": "acceptedGroupId",
            "in": "path",
            "required": true,
            "schema": {
              "type": "integer",
              "format": "int32"
            }
          }
        ],
        "responses": {
          "200": {
            "description": "OK"
          }
        }
      }
    },
    "/api/groups/student/{studentId}/supervision-status": {
      "get": {
        "tags": [
          "Group"
        ],
        "parameters": [
          {
            "name": "studentId",
            "in": "path",
            "required": true,
            "schema": {
              "type": "integer",
              "format": "int32"
            }
          }
        ],
        "responses": {
          "200": {
            "description": "OK"
          }
        }
      }
    },
    "/api/groups/with-supervisors": {
      "get": {
        "tags": [
          "Group"
        ],
        "responses": {
          "200": {
            "description": "OK",
            "content": {
              "text/plain": {
                "schema": {
                  "type": "array",
                  "items": {
                    "$ref": "#/components/schemas/GroupDetailsDto"
                  }
                }
              },
              "application/json": {
                "schema": {
                  "type": "array",
                  "items": {
                    "$ref": "#/components/schemas/GroupDetailsDto"
                  }
                }
              },
              "text/json": {
                "schema": {
                  "type": "array",
                  "items": {
                    "$ref": "#/components/schemas/GroupDetailsDto"
                  }
                }
              }
            }
          }
        }
      }
    },
    "/api/student/evaluations/progress": {
      "get": {
        "tags": [
          "StudentEvaluation"
        ],
        "responses": {
          "200": {
            "description": "OK",
            "content": {
              "text/plain": {
                "schema": {
                  "type": "array",
                  "items": {
                    "$ref": "#/components/schemas/StudentEvaluationDto"
                  }
                }
              },
              "application/json": {
                "schema": {
                  "type": "array",
                  "items": {
                    "$ref": "#/components/schemas/StudentEvaluationDto"
                  }
                }
              },
              "text/json": {
                "schema": {
                  "type": "array",
                  "items": {
                    "$ref": "#/components/schemas/StudentEvaluationDto"
                  }
                }
              }
            }
          }
        }
      }
    },
    "/api/student/evaluations/dashboard": {
      "get": {
        "tags": [
          "StudentEvaluation"
        ],
        "responses": {
          "200": {
            "description": "OK",
            "content": {
              "text/plain": {
                "schema": {
                  "$ref": "#/components/schemas/StudentPerformanceDashboardDto"
                }
              },
              "application/json": {
                "schema": {
                  "$ref": "#/components/schemas/StudentPerformanceDashboardDto"
                }
              },
              "text/json": {
                "schema": {
                  "$ref": "#/components/schemas/StudentPerformanceDashboardDto"
                }
              }
            }
          }
        }
      }
    },
    "/api/student/evaluations/final-grade": {
      "get": {
        "tags": [
          "StudentEvaluation"
        ],
        "responses": {
          "200": {
            "description": "OK",
            "content": {
              "text/plain": {
                "schema": {
                  "type": "number",
                  "format": "double"
                }
              },
              "application/json": {
                "schema": {
                  "type": "number",
                  "format": "double"
                }
              },
              "text/json": {
                "schema": {
                  "type": "number",
                  "format": "double"
                }
              }
            }
          }
        }
      }
    },
    "/api/teachers": {
      "get": {
        "tags": [
          "Teacher"
        ],
        "responses": {
          "200": {
            "description": "OK"
          }
        }
      }
    },
    "/api/teachers/request-supervision": {
      "post": {
        "tags": [
          "Teacher"
        ],
        "requestBody": {
          "content": {
            "application/json": {
              "schema": {
                "$ref": "#/components/schemas/SupervisionRequestDto"
              }
            },
            "text/json": {
              "schema": {
                "$ref": "#/components/schemas/SupervisionRequestDto"
              }
            },
            "application/*+json": {
              "schema": {
                "$ref": "#/components/schemas/SupervisionRequestDto"
              }
            }
          }
        },
        "responses": {
          "200": {
            "description": "OK"
          }
        }
      }
    },
    "/api/teachers/{id}": {
      "get": {
        "tags": [
          "Teacher"
        ],
        "parameters": [
          {
            "name": "id",
            "in": "path",
            "required": true,
            "schema": {
              "type": "integer",
              "format": "int32"
            }
          }
        ],
        "responses": {
          "200": {
            "description": "OK"
          }
        }
      }
    },
    "/api/teacher-dashboard/supervision-requests": {
      "get": {
        "tags": [
          "TeacherDashboard"
        ],
        "responses": {
          "200": {
            "description": "OK"
          }
        }
      }
    },
    "/api/teacher-dashboard/respond-to-request": {
      "post": {
        "tags": [
          "TeacherDashboard"
        ],
        "requestBody": {
          "content": {
            "application/json": {
              "schema": {
                "$ref": "#/components/schemas/SupervisionResponseDto"
              }
            },
            "text/json": {
              "schema": {
                "$ref": "#/components/schemas/SupervisionResponseDto"
              }
            },
            "application/*+json": {
              "schema": {
                "$ref": "#/components/schemas/SupervisionResponseDto"
              }
            }
          }
        },
        "responses": {
          "200": {
            "description": "OK"
          }
        }
      }
    },
    "/api/teacher-dashboard/my-groups": {
      "get": {
        "tags": [
          "TeacherDashboard"
        ],
        "responses": {
          "200": {
            "description": "OK"
          }
        }
      }
    },
    "/api/teacher/evaluations/panel-assignments": {
      "get": {
        "tags": [
          "TeacherEvaluation"
        ],
        "responses": {
          "200": {
            "description": "OK",
            "content": {
              "text/plain": {
                "schema": {
                  "type": "array",
                  "items": {
                    "$ref": "#/components/schemas/GroupEvaluationDto"
                  }
                }
              },
              "application/json": {
                "schema": {
                  "type": "array",
                  "items": {
                    "$ref": "#/components/schemas/GroupEvaluationDto"
                  }
                }
              },
              "text/json": {
                "schema": {
                  "type": "array",
                  "items": {
                    "$ref": "#/components/schemas/GroupEvaluationDto"
                  }
                }
              }
            }
          }
        }
      }
    },
    "/api/teacher/evaluations/panels": {
      "get": {
        "tags": [
          "TeacherEvaluation"
        ],
        "responses": {
          "200": {
            "description": "OK",
            "content": {
              "text/plain": {
                "schema": {
                  "type": "array",
                  "items": {
                    "$ref": "#/components/schemas/PanelDto"
                  }
                }
              },
              "application/json": {
                "schema": {
                  "type": "array",
                  "items": {
                    "$ref": "#/components/schemas/PanelDto"
                  }
                }
              },
              "text/json": {
                "schema": {
                  "type": "array",
                  "items": {
                    "$ref": "#/components/schemas/PanelDto"
                  }
                }
              }
            }
          }
        }
      }
    },
    "/api/teacher/evaluations/evaluate-student": {
      "post": {
        "tags": [
          "TeacherEvaluation"
        ],
        "requestBody": {
          "content": {
            "application/json": {
              "schema": {
                "$ref": "#/components/schemas/EvaluateStudentDto"
              }
            },
            "text/json": {
              "schema": {
                "$ref": "#/components/schemas/EvaluateStudentDto"
              }
            },
            "application/*+json": {
              "schema": {
                "$ref": "#/components/schemas/EvaluateStudentDto"
              }
            }
          }
        },
        "responses": {
          "200": {
            "description": "OK",
            "content": {
              "text/plain": {
                "schema": {
                  "$ref": "#/components/schemas/StudentEvaluationDto"
                }
              },
              "application/json": {
                "schema": {
                  "$ref": "#/components/schemas/StudentEvaluationDto"
                }
              },
              "text/json": {
                "schema": {
                  "$ref": "#/components/schemas/StudentEvaluationDto"
                }
              }
            }
          }
        }
      }
    },
    "/api/teacher/evaluations/group-evaluations/{id}": {
      "get": {
        "tags": [
          "TeacherEvaluation"
        ],
        "parameters": [
          {
            "name": "id",
            "in": "path",
            "required": true,
            "schema": {
              "type": "integer",
              "format": "int32"
            }
          }
        ],
        "responses": {
          "200": {
            "description": "OK",
            "content": {
              "text/plain": {
                "schema": {
                  "$ref": "#/components/schemas/GroupEvaluationDto"
                }
              },
              "application/json": {
                "schema": {
                  "$ref": "#/components/schemas/GroupEvaluationDto"
                }
              },
              "text/json": {
                "schema": {
                  "$ref": "#/components/schemas/GroupEvaluationDto"
                }
              }
            }
          }
        }
      }
    },
    "/api/teacher/evaluations/supervised-groups/performance": {
      "get": {
        "tags": [
          "TeacherEvaluation"
        ],
        "responses": {
          "200": {
            "description": "OK",
            "content": {
              "text/plain": {
                "schema": {
                  "type": "array",
                  "items": {
                    "$ref": "#/components/schemas/GroupPerformanceDto"
                  }
                }
              },
              "application/json": {
                "schema": {
                  "type": "array",
                  "items": {
                    "$ref": "#/components/schemas/GroupPerformanceDto"
                  }
                }
              },
              "text/json": {
                "schema": {
                  "type": "array",
                  "items": {
                    "$ref": "#/components/schemas/GroupPerformanceDto"
                  }
                }
              }
            }
          }
        }
      }
    },
    "/api/teacher/evaluations/group-evaluations/{id}/comments": {
      "put": {
        "tags": [
          "TeacherEvaluation"
        ],
        "parameters": [
          {
            "name": "id",
            "in": "path",
            "required": true,
            "schema": {
              "type": "integer",
              "format": "int32"
            }
          }
        ],
        "requestBody": {
          "content": {
            "application/json": {
              "schema": {
                "$ref": "#/components/schemas/UpdateGroupEvaluationCommentsDto"
              }
            },
            "text/json": {
              "schema": {
                "$ref": "#/components/schemas/UpdateGroupEvaluationCommentsDto"
              }
            },
            "application/*+json": {
              "schema": {
                "$ref": "#/components/schemas/UpdateGroupEvaluationCommentsDto"
              }
            }
          }
        },
        "responses": {
          "200": {
            "description": "OK",
            "content": {
              "text/plain": {
                "schema": {
                  "$ref": "#/components/schemas/GroupEvaluationDto"
                }
              },
              "application/json": {
                "schema": {
                  "$ref": "#/components/schemas/GroupEvaluationDto"
                }
              },
              "text/json": {
                "schema": {
                  "$ref": "#/components/schemas/GroupEvaluationDto"
                }
              }
            }
          }
        }
      }
    },
    "/api/teacher/evaluations/dashboard": {
      "get": {
        "tags": [
          "TeacherEvaluation"
        ],
        "responses": {
          "200": {
            "description": "OK",
            "content": {
              "text/plain": {
                "schema": {
                  "$ref": "#/components/schemas/TeacherDashboardDto"
                }
              },
              "application/json": {
                "schema": {
                  "$ref": "#/components/schemas/TeacherDashboardDto"
                }
              },
              "text/json": {
                "schema": {
                  "$ref": "#/components/schemas/TeacherDashboardDto"
                }
              }
            }
          }
        }
      }
    },
    "/api/teacher/evaluations/evaluate-student-with-rubric": {
      "post": {
        "tags": [
          "TeacherEvaluation"
        ],
        "requestBody": {
          "content": {
            "application/json": {
              "schema": {
                "$ref": "#/components/schemas/EvaluateStudentDto"
              }
            },
            "text/json": {
              "schema": {
                "$ref": "#/components/schemas/EvaluateStudentDto"
              }
            },
            "application/*+json": {
              "schema": {
                "$ref": "#/components/schemas/EvaluateStudentDto"
              }
            }
          }
        },
        "responses": {
          "200": {
            "description": "OK",
            "content": {
              "text/plain": {
                "schema": {
                  "$ref": "#/components/schemas/EnhancedStudentEvaluationDto"
                }
              },
              "application/json": {
                "schema": {
                  "$ref": "#/components/schemas/EnhancedStudentEvaluationDto"
                }
              },
              "text/json": {
                "schema": {
                  "$ref": "#/components/schemas/EnhancedStudentEvaluationDto"
                }
              }
            }
          }
        }
      }
    },
    "/api/teacher/evaluations/group-evaluations/{id}/students": {
      "get": {
        "tags": [
          "TeacherEvaluation"
        ],
        "parameters": [
          {
            "name": "id",
            "in": "path",
            "required": true,
            "schema": {
              "type": "integer",
              "format": "int32"
            }
          }
        ],
        "responses": {
          "200": {
            "description": "OK",
            "content": {
              "text/plain": {
                "schema": {
                  "type": "array",
                  "items": {
                    "$ref": "#/components/schemas/StudentDto"
                  }
                }
              },
              "application/json": {
                "schema": {
                  "type": "array",
                  "items": {
                    "$ref": "#/components/schemas/StudentDto"
                  }
                }
              },
              "text/json": {
                "schema": {
                  "type": "array",
                  "items": {
                    "$ref": "#/components/schemas/StudentDto"
                  }
                }
              }
            }
          }
        }
      }
    },
    "/api/teacher/evaluations/event-evaluation-type/{id}": {
      "get": {
        "tags": [
          "TeacherEvaluation"
        ],
        "parameters": [
          {
            "name": "id",
            "in": "path",
            "required": true,
            "schema": {
              "type": "integer",
              "format": "int32"
            }
          }
        ],
        "responses": {
          "200": {
            "description": "OK",
            "content": {
              "text/plain": {
                "schema": {
                  "$ref": "#/components/schemas/EventEvaluationTypeDto"
                }
              },
              "application/json": {
                "schema": {
                  "$ref": "#/components/schemas/EventEvaluationTypeDto"
                }
              },
              "text/json": {
                "schema": {
                  "$ref": "#/components/schemas/EventEvaluationTypeDto"
                }
              }
            }
          }
        }
      }
    },
    "/api/teacher/evaluations/evaluations/{id}/complete": {
      "put": {
        "tags": [
          "TeacherEvaluation"
        ],
        "parameters": [
          {
            "name": "id",
            "in": "path",
            "required": true,
            "schema": {
              "type": "integer",
              "format": "int32"
            }
          }
        ],
        "responses": {
          "200": {
            "description": "OK"
          }
        }
      }
    },
    "/api/users": {
      "get": {
        "tags": [
          "UserManagement"
        ],
        "responses": {
          "200": {
            "description": "OK"
          }
        }
      }
    },
    "/api/users/{userId}": {
      "get": {
        "tags": [
          "UserManagement"
        ],
        "parameters": [
          {
            "name": "userId",
            "in": "path",
            "required": true,
            "schema": {
              "type": "integer",
              "format": "int32"
            }
          }
        ],
        "responses": {
          "200": {
            "description": "OK"
          }
        }
      },
      "put": {
        "tags": [
          "UserManagement"
        ],
        "parameters": [
          {
            "name": "userId",
            "in": "path",
            "required": true,
            "schema": {
              "type": "integer",
              "format": "int32"
            }
          }
        ],
        "requestBody": {
          "content": {
            "application/json": {
              "schema": {
                "$ref": "#/components/schemas/UserUpdateDto"
              }
            },
            "text/json": {
              "schema": {
                "$ref": "#/components/schemas/UserUpdateDto"
              }
            },
            "application/*+json": {
              "schema": {
                "$ref": "#/components/schemas/UserUpdateDto"
              }
            }
          }
        },
        "responses": {
          "200": {
            "description": "OK"
          }
        }
      },
      "delete": {
        "tags": [
          "UserManagement"
        ],
        "parameters": [
          {
            "name": "userId",
            "in": "path",
            "required": true,
            "schema": {
              "type": "integer",
              "format": "int32"
            }
          }
        ],
        "responses": {
          "200": {
            "description": "OK"
          }
        }
      }
    }
  },
  "components": {
    "schemas": {
      "AdminDashboardDto": {
        "type": "object",
        "properties": {
          "totalPanels": {
            "type": "integer",
            "format": "int32"
          },
          "totalEvents": {
            "type": "integer",
            "format": "int32"
          },
          "totalGroups": {
            "type": "integer",
            "format": "int32"
          },
          "supervisedGroups": {
            "type": "integer",
            "format": "int32"
          },
          "completedEvaluations": {
            "type": "integer",
            "format": "int32"
          },
          "pendingEvaluations": {
            "type": "integer",
            "format": "int32"
          },
          "eventStatistics": {
            "type": "array",
            "items": {
              "$ref": "#/components/schemas/EventStatisticsDto"
            },
            "nullable": true
          }
        },
        "additionalProperties": false
      },
      "AssignPanelDto": {
        "type": "object",
        "properties": {
          "groupId": {
            "type": "integer",
            "format": "int32"
          },
          "panelId": {
            "type": "integer",
            "format": "int32"
          },
          "eventId": {
            "type": "integer",
            "format": "int32"
          },
          "scheduledDate": {
            "type": "string",
            "format": "date-time"
          }
        },
        "additionalProperties": false
      },
      "CategoryEvaluatorDetailDto": {
        "type": "object",
        "properties": {
          "evaluatorId": {
            "type": "integer",
            "format": "int32"
          },
          "evaluatorName": {
            "type": "string",
            "nullable": true
          },
          "score": {
            "type": "integer",
            "format": "int32"
          },
          "feedback": {
            "type": "string",
            "nullable": true
          },
          "evaluatedAt": {
            "type": "string",
            "format": "date-time"
          }
        },
        "additionalProperties": false
      },
      "CategoryScoreDetailDto": {
        "type": "object",
        "properties": {
          "categoryId": {
            "type": "integer",
            "format": "int32"
          },
          "categoryName": {
            "type": "string",
            "nullable": true
          },
          "categoryWeight": {
            "type": "number",
            "format": "double"
          },
          "score": {
            "type": "integer",
            "format": "int32"
          },
          "maxScore": {
            "type": "integer",
            "format": "int32"
          },
          "weightedScore": {
            "type": "number",
            "format": "double"
          },
          "feedback": {
            "type": "string",
            "nullable": true
          },
          "evaluator": {
            "$ref": "#/components/schemas/EvaluatorDto"
          },
          "evaluatorDetails": {
            "type": "array",
            "items": {
              "$ref": "#/components/schemas/CategoryEvaluatorDetailDto"
            },
            "nullable": true
          }
        },
        "additionalProperties": false
      },
      "CategoryScoreDto": {
        "type": "object",
        "properties": {
          "categoryId": {
            "type": "integer",
            "format": "int32"
          },
          "score": {
            "type": "integer",
            "format": "int32"
          },
          "feedback": {
            "type": "string",
            "nullable": true
          }
        },
        "additionalProperties": false
      },
      "CreateEventDto": {
        "type": "object",
        "properties": {
          "name": {
            "type": "string",
            "nullable": true
          },
          "description": {
            "type": "string",
            "nullable": true
          },
          "date": {
            "type": "string",
            "format": "date-time"
          },
          "totalMarks": {
            "type": "integer",
            "format": "int32"
          },
          "isActive": {
            "type": "boolean"
          },
          "weight": {
            "type": "number",
            "format": "double"
          },
          "type": {
            "$ref": "#/components/schemas/EventType"
          },
          "rubricId": {
            "type": "integer",
            "format": "int32",
            "nullable": true
          }
        },
        "additionalProperties": false
      },
      "CreateGroupDto": {
        "required": [
          "groupName",
          "memberEmails"
        ],
        "type": "object",
        "properties": {
          "groupName": {
            "minLength": 1,
            "type": "string"
          },
          "memberEmails": {
            "type": "array",
            "items": {
              "type": "string"
            }
          }
        },
        "additionalProperties": false
      },
      "CreatePanelDto": {
        "type": "object",
        "properties": {
          "name": {
            "type": "string",
            "nullable": true
          },
          "teacherIds": {
            "type": "array",
            "items": {
              "type": "integer",
              "format": "int32"
            },
            "nullable": true
          }
        },
        "additionalProperties": false
      },
      "CreateRubricCategoryDto": {
        "type": "object",
        "properties": {
          "name": {
            "type": "string",
            "nullable": true
          },
          "description": {
            "type": "string",
            "nullable": true
          },
          "weight": {
            "type": "number",
            "format": "double"
          },
          "maxScore": {
            "type": "integer",
            "format": "int32"
          }
        },
        "additionalProperties": false
      },
      "CreateRubricDto": {
        "type": "object",
        "properties": {
          "name": {
            "type": "string",
            "nullable": true
          },
          "description": {
            "type": "string",
            "nullable": true
          },
          "categories": {
            "type": "array",
            "items": {
              "$ref": "#/components/schemas/CreateRubricCategoryDto"
            },
            "nullable": true
          }
        },
        "additionalProperties": false
      },
      "EnhancedStudentEvaluationDto": {
        "type": "object",
        "properties": {
          "id": {
            "type": "integer",
            "format": "int32"
          },
          "studentId": {
            "type": "integer",
            "format": "int32"
          },
          "studentName": {
            "type": "string",
            "nullable": true
          },
          "obtainedMarks": {
            "type": "integer",
            "format": "int32"
          },
          "feedback": {
            "type": "string",
            "nullable": true
          },
          "evaluatedAt": {
            "type": "string",
            "format": "date-time"
          },
          "eventName": {
            "type": "string",
            "nullable": true
          },
          "eventDate": {
            "type": "string",
            "format": "date-time",
            "nullable": true
          },
          "totalMarks": {
            "type": "integer",
            "format": "int32",
            "nullable": true
          },
          "percentageObtained": {
            "type": "number",
            "format": "double",
            "nullable": true
          },
          "isComplete": {
            "type": "boolean"
          },
          "categoryScores": {
            "type": "array",
            "items": {
              "$ref": "#/components/schemas/CategoryScoreDetailDto"
            },
            "nullable": true
          },
          "evaluators": {
            "type": "array",
            "items": {
              "$ref": "#/components/schemas/EvaluatorDto"
            },
            "nullable": true
          },
          "weightedScore": {
            "type": "number",
            "format": "double"
          }
        },
        "additionalProperties": false
      },
      "EvaluateStudentDto": {
        "type": "object",
        "properties": {
          "groupEvaluationId": {
            "type": "integer",
            "format": "int32"
          },
          "studentId": {
            "type": "integer",
            "format": "int32"
          },
          "obtainedMarks": {
            "type": "integer",
            "format": "int32",
            "nullable": true
          },
          "feedback": {
            "type": "string",
            "nullable": true
          },
          "categoryScores": {
            "type": "array",
            "items": {
              "$ref": "#/components/schemas/CategoryScoreDto"
            },
            "nullable": true
          }
        },
        "additionalProperties": false
      },
      "EvaluationEventDto": {
        "type": "object",
        "properties": {
          "id": {
            "type": "integer",
            "format": "int32"
          },
          "name": {
            "type": "string",
            "nullable": true
          },
          "description": {
            "type": "string",
            "nullable": true
          },
          "date": {
            "type": "string",
            "format": "date-time"
          },
          "totalMarks": {
            "type": "integer",
            "format": "int32"
          },
          "isActive": {
            "type": "boolean"
          },
          "createdAt": {
            "type": "string",
            "format": "date-time"
          },
          "weight": {
            "type": "number",
            "format": "double"
          },
          "type": {
            "$ref": "#/components/schemas/EventType"
          },
          "rubricId": {
            "type": "integer",
            "format": "int32",
            "nullable": true
          },
          "rubricName": {
            "type": "string",
            "nullable": true
          }
        },
        "additionalProperties": false
      },
      "EvaluationRubricDto": {
        "type": "object",
        "properties": {
          "id": {
            "type": "integer",
            "format": "int32"
          },
          "name": {
            "type": "string",
            "nullable": true
          },
          "description": {
            "type": "string",
            "nullable": true
          },
          "isActive": {
            "type": "boolean"
          },
          "createdAt": {
            "type": "string",
            "format": "date-time"
          },
          "categories": {
            "type": "array",
            "items": {
              "$ref": "#/components/schemas/RubricCategoryDto"
            },
            "nullable": true
          }
        },
        "additionalProperties": false
      },
      "EvaluatorDto": {
        "type": "object",
        "properties": {
          "id": {
            "type": "integer",
            "format": "int32"
          },
          "name": {
            "type": "string",
            "nullable": true
          }
        },
        "additionalProperties": false
      },
      "EventEvaluationTypeDto": {
        "type": "object",
        "properties": {
          "groupEvaluationId": {
            "type": "integer",
            "format": "int32"
          },
          "eventId": {
            "type": "integer",
            "format": "int32"
          },
          "eventName": {
            "type": "string",
            "nullable": true
          },
          "hasRubric": {
            "type": "boolean"
          },
          "rubricId": {
            "type": "integer",
            "format": "int32",
            "nullable": true
          },
          "totalMarks": {
            "type": "integer",
            "format": "int32"
          }
        },
        "additionalProperties": false
      },
      "EventPerformanceDto": {
        "type": "object",
        "properties": {
          "eventId": {
            "type": "integer",
            "format": "int32"
          },
          "eventName": {
            "type": "string",
            "nullable": true
          },
          "averageMarks": {
            "type": "number",
            "format": "double"
          },
          "totalMarks": {
            "type": "integer",
            "format": "int32"
          },
          "percentage": {
            "type": "number",
            "format": "double"
          },
          "evaluatedOn": {
            "type": "string",
            "format": "date-time"
          },
          "isCompleted": {
            "type": "boolean"
          },
          "studentPerformances": {
            "type": "array",
            "items": {
              "$ref": "#/components/schemas/StudentPerformanceDto"
            },
            "nullable": true
          }
        },
        "additionalProperties": false
      },
      "EventStatisticsDto": {
        "type": "object",
        "properties": {
          "eventId": {
            "type": "integer",
            "format": "int32"
          },
          "eventName": {
            "type": "string",
            "nullable": true
          },
          "totalGroups": {
            "type": "integer",
            "format": "int32"
          },
          "evaluatedGroups": {
            "type": "integer",
            "format": "int32"
          },
          "averagePerformance": {
            "type": "number",
            "format": "double"
          },
          "date": {
            "type": "string",
            "format": "date-time"
          }
        },
        "additionalProperties": false
      },
      "EventSummaryDto": {
        "type": "object",
        "properties": {
          "eventName": {
            "type": "string",
            "nullable": true
          },
          "obtainedMarks": {
            "type": "integer",
            "format": "int32"
          },
          "totalMarks": {
            "type": "integer",
            "format": "int32"
          },
          "percentage": {
            "type": "number",
            "format": "double"
          }
        },
        "additionalProperties": false
      },
      "EventType": {
        "enum": [
          0,
          1,
          2
        ],
        "type": "integer",
        "format": "int32"
      },
      "GroupDetailsDto": {
        "type": "object",
        "properties": {
          "id": {
            "type": "integer",
            "format": "int32"
          },
          "name": {
            "type": "string",
            "nullable": true
          },
          "createdAt": {
            "type": "string",
            "format": "date-time"
          },
          "members": {
            "type": "array",
            "items": {
              "$ref": "#/components/schemas/StudentDetailsDto"
            },
            "nullable": true
          },
          "teacherId": {
            "type": "integer",
            "format": "int32",
            "nullable": true
          },
          "teacherName": {
            "type": "string",
            "nullable": true
          },
          "supervisionStatus": {
            "type": "string",
            "nullable": true
          }
        },
        "additionalProperties": false
      },
      "GroupEvaluationDto": {
        "type": "object",
        "properties": {
          "id": {
            "type": "integer",
            "format": "int32"
          },
          "groupId": {
            "type": "integer",
            "format": "int32"
          },
          "groupName": {
            "type": "string",
            "nullable": true
          },
          "panelId": {
            "type": "integer",
            "format": "int32"
          },
          "panelName": {
            "type": "string",
            "nullable": true
          },
          "eventId": {
            "type": "integer",
            "format": "int32"
          },
          "eventName": {
            "type": "string",
            "nullable": true
          },
          "scheduledDate": {
            "type": "string",
            "format": "date-time"
          },
          "isCompleted": {
            "type": "boolean"
          },
          "comments": {
            "type": "string",
            "nullable": true
          },
          "studentEvaluations": {
            "type": "array",
            "items": {
              "$ref": "#/components/schemas/StudentEvaluationDto"
            },
            "nullable": true
          }
        },
        "additionalProperties": false
      },
      "GroupPerformanceDto": {
        "type": "object",
        "properties": {
          "groupId": {
            "type": "integer",
            "format": "int32"
          },
          "groupName": {
            "type": "string",
            "nullable": true
          },
          "events": {
            "type": "array",
            "items": {
              "$ref": "#/components/schemas/EventPerformanceDto"
            },
            "nullable": true
          },
          "averagePerformance": {
            "type": "number",
            "format": "double"
          },
          "completedEvents": {
            "type": "integer",
            "format": "int32"
          },
          "totalEvents": {
            "type": "integer",
            "format": "int32"
          }
        },
        "additionalProperties": false
      },
      "LoginDto": {
        "type": "object",
        "properties": {
          "email": {
            "type": "string",
            "nullable": true
          },
          "password": {
            "type": "string",
            "nullable": true
          }
        },
        "additionalProperties": false
      },
      "NormalizedGradeDto": {
        "type": "object",
        "properties": {
          "studentId": {
            "type": "integer",
            "format": "int32"
          },
          "studentName": {
            "type": "string",
            "nullable": true
          },
          "rawGrade": {
            "type": "number",
            "format": "double"
          },
          "normalizedGrade": {
            "type": "number",
            "format": "double"
          }
        },
        "additionalProperties": false
      },
      "PanelDto": {
        "type": "object",
        "properties": {
          "id": {
            "type": "integer",
            "format": "int32"
          },
          "name": {
            "type": "string",
            "nullable": true
          },
          "createdAt": {
            "type": "string",
            "format": "date-time"
          },
          "members": {
            "type": "array",
            "items": {
              "$ref": "#/components/schemas/PanelMemberDto"
            },
            "nullable": true
          }
        },
        "additionalProperties": false
      },
      "PanelMemberDto": {
        "type": "object",
        "properties": {
          "teacherId": {
            "type": "integer",
            "format": "int32"
          },
          "teacherName": {
            "type": "string",
            "nullable": true
          },
          "isHead": {
            "type": "boolean"
          }
        },
        "additionalProperties": false
      },
      "RegisterAdminDto": {
        "type": "object",
        "properties": {
          "fullName": {
            "type": "string",
            "nullable": true
          },
          "email": {
            "type": "string",
            "nullable": true
          },
          "password": {
            "type": "string",
            "nullable": true
          }
        },
        "additionalProperties": false
      },
      "RegisterStudentDto": {
        "type": "object",
        "properties": {
          "fullName": {
            "type": "string",
            "nullable": true
          },
          "email": {
            "type": "string",
            "nullable": true
          },
          "password": {
            "type": "string",
            "nullable": true
          },
          "enrollmentNumber": {
            "type": "string",
            "nullable": true
          },
          "department": {
            "type": "string",
            "nullable": true
          }
        },
        "additionalProperties": false
      },
      "RegisterTeacherDto": {
        "type": "object",
        "properties": {
          "fullName": {
            "type": "string",
            "nullable": true
          },
          "email": {
            "type": "string",
            "nullable": true
          },
          "password": {
            "type": "string",
            "nullable": true
          },
          "qualification": {
            "type": "string",
            "nullable": true
          },
          "areaOfSpecialization": {
            "type": "string",
            "nullable": true
          },
          "officeLocation": {
            "type": "string",
            "nullable": true
          }
        },
        "additionalProperties": false
      },
      "RubricCategoryDto": {
        "type": "object",
        "properties": {
          "id": {
            "type": "integer",
            "format": "int32"
          },
          "name": {
            "type": "string",
            "nullable": true
          },
          "description": {
            "type": "string",
            "nullable": true
          },
          "weight": {
            "type": "number",
            "format": "double"
          },
          "maxScore": {
            "type": "integer",
            "format": "int32"
          }
        },
        "additionalProperties": false
      },
      "StudentDetailsDto": {
        "type": "object",
        "properties": {
          "id": {
            "type": "integer",
            "format": "int32"
          },
          "fullName": {
            "type": "string",
            "nullable": true
          },
          "email": {
            "type": "string",
            "nullable": true
          },
          "enrollmentNumber": {
            "type": "string",
            "nullable": true
          },
          "department": {
            "type": "string",
            "nullable": true
          },
          "isCreator": {
            "type": "boolean"
          }
        },
        "additionalProperties": false
      },
      "StudentDto": {
        "type": "object",
        "properties": {
          "id": {
            "type": "integer",
            "format": "int32"
          },
          "fullName": {
            "type": "string",
            "nullable": true
          },
          "email": {
            "type": "string",
            "nullable": true
          },
          "enrollmentNumber": {
            "type": "string",
            "nullable": true
          },
          "department": {
            "type": "string",
            "nullable": true
          },
          "isEvaluated": {
            "type": "boolean"
          }
        },
        "additionalProperties": false
      },
      "StudentEvaluationDto": {
        "type": "object",
        "properties": {
          "id": {
            "type": "integer",
            "format": "int32"
          },
          "studentId": {
            "type": "integer",
            "format": "int32"
          },
          "studentName": {
            "type": "string",
            "nullable": true
          },
          "obtainedMarks": {
            "type": "integer",
            "format": "int32"
          },
          "feedback": {
            "type": "string",
            "nullable": true
          },
          "evaluatedAt": {
            "type": "string",
            "format": "date-time"
          },
          "eventName": {
            "type": "string",
            "nullable": true
          },
          "eventDate": {
            "type": "string",
            "format": "date-time",
            "nullable": true
          },
          "totalMarks": {
            "type": "integer",
            "format": "int32",
            "nullable": true
          },
          "percentageObtained": {
            "type": "number",
            "format": "double",
            "nullable": true
          },
          "isComplete": {
            "type": "boolean"
          }
        },
        "additionalProperties": false
      },
      "StudentPerformanceDashboardDto": {
        "type": "object",
        "properties": {
          "studentId": {
            "type": "integer",
            "format": "int32"
          },
          "totalEvaluations": {
            "type": "integer",
            "format": "int32"
          },
          "averagePerformance": {
            "type": "number",
            "format": "double"
          },
          "eventSummaries": {
            "type": "array",
            "items": {
              "$ref": "#/components/schemas/EventSummaryDto"
            },
            "nullable": true
          },
          "detailedEvaluations": {
            "type": "array",
            "items": {
              "$ref": "#/components/schemas/StudentEvaluationDto"
            },
            "nullable": true
          }
        },
        "additionalProperties": false
      },
      "StudentPerformanceDto": {
        "type": "object",
        "properties": {
          "studentId": {
            "type": "integer",
            "format": "int32"
          },
          "studentName": {
            "type": "string",
            "nullable": true
          },
          "obtainedMarks": {
            "type": "integer",
            "format": "int32"
          },
          "percentage": {
            "type": "number",
            "format": "double"
          },
          "feedback": {
            "type": "string",
            "nullable": true
          }
        },
        "additionalProperties": false
      },
      "SupervisionRequestDto": {
        "type": "object",
        "properties": {
          "groupId": {
            "type": "integer",
            "format": "int32"
          },
          "teacherId": {
            "type": "integer",
            "format": "int32"
          },
          "message": {
            "type": "string",
            "nullable": true
          }
        },
        "additionalProperties": false
      },
      "SupervisionResponseDto": {
        "type": "object",
        "properties": {
          "groupId": {
            "type": "integer",
            "format": "int32"
          },
          "isApproved": {
            "type": "boolean"
          },
          "message": {
            "type": "string",
            "nullable": true
          }
        },
        "additionalProperties": false
      },
      "TeacherDashboardDto": {
        "type": "object",
        "properties": {
          "supervisedGroupCount": {
            "type": "integer",
            "format": "int32"
          },
          "panelMembershipCount": {
            "type": "integer",
            "format": "int32"
          },
          "totalEvaluationsCount": {
            "type": "integer",
            "format": "int32"
          },
          "supervisedGroups": {
            "type": "array",
            "items": {
              "$ref": "#/components/schemas/GroupPerformanceDto"
            },
            "nullable": true
          }
        },
        "additionalProperties": false
      },
      "UpdateEventDto": {
        "type": "object",
        "properties": {
          "name": {
            "type": "string",
            "nullable": true
          },
          "description": {
            "type": "string",
            "nullable": true
          },
          "date": {
            "type": "string",
            "format": "date-time"
          },
          "totalMarks": {
            "type": "integer",
            "format": "int32"
          },
          "isActive": {
            "type": "boolean"
          },
          "type": {
            "$ref": "#/components/schemas/EventType"
          },
          "weight": {
            "type": "number",
            "format": "double"
          },
          "rubricId": {
            "type": "integer",
            "format": "int32",
            "nullable": true
          }
        },
        "additionalProperties": false
      },
      "UpdateGroupEvaluationCommentsDto": {
        "type": "object",
        "properties": {
          "comments": {
            "type": "string",
            "nullable": true
          }
        },
        "additionalProperties": false
      },
      "UpdatePanelDto": {
        "type": "object",
        "properties": {
          "name": {
            "type": "string",
            "nullable": true
          },
          "teacherIds": {
            "type": "array",
            "items": {
              "type": "integer",
              "format": "int32"
            },
            "nullable": true
          }
        },
        "additionalProperties": false
      },
      "UpdateRubricCategoryDto": {
        "type": "object",
        "properties": {
          "id": {
            "type": "integer",
            "format": "int32"
          },
          "name": {
            "type": "string",
            "nullable": true
          },
          "description": {
            "type": "string",
            "nullable": true
          },
          "weight": {
            "type": "number",
            "format": "double"
          },
          "maxScore": {
            "type": "integer",
            "format": "int32"
          }
        },
        "additionalProperties": false
      },
      "UpdateRubricDto": {
        "type": "object",
        "properties": {
          "name": {
            "type": "string",
            "nullable": true
          },
          "description": {
            "type": "string",
            "nullable": true
          },
          "isActive": {
            "type": "boolean"
          },
          "categories": {
            "type": "array",
            "items": {
              "$ref": "#/components/schemas/UpdateRubricCategoryDto"
            },
            "nullable": true
          }
        },
        "additionalProperties": false
      },
      "UserUpdateDto": {
        "type": "object",
        "properties": {
          "id": {
            "type": "integer",
            "format": "int32"
          },
          "fullName": {
            "type": "string",
            "nullable": true
          },
          "email": {
            "type": "string",
            "nullable": true
          },
          "additionalInfo": {
            "type": "object",
            "additionalProperties": { },
            "nullable": true
          }
        },
        "additionalProperties": false
      }
    }
  }
}